JavaBianchengSixiang/README.md
JavaBianchengSixiang/__init__.py
JavaBianchengSixiang/__main__.py
JavaBianchengSixiang/file.epub
JavaBianchengSixiang/index.html
JavaBianchengSixiang/css/__init__.py
JavaBianchengSixiang/css/annotations.css
JavaBianchengSixiang/css/main.css
JavaBianchengSixiang/css/normalize.css
JavaBianchengSixiang/css/popup.css
JavaBianchengSixiang/font/__init__.py
JavaBianchengSixiang/font/fontello.eot
JavaBianchengSixiang/font/fontello.svg
JavaBianchengSixiang/font/fontello.ttf
JavaBianchengSixiang/font/fontello.woff
JavaBianchengSixiang/img/__init__.py
JavaBianchengSixiang/img/annotator-glyph-sprite.png
JavaBianchengSixiang/img/annotator-icon-sprite.png
JavaBianchengSixiang/img/apple-touch-icon.png
JavaBianchengSixiang/img/cancelfullscreen.png
JavaBianchengSixiang/img/close.png
JavaBianchengSixiang/img/fullscreen.png
JavaBianchengSixiang/img/loader.gif
JavaBianchengSixiang/img/menu-icon.png
JavaBianchengSixiang/img/save.png
JavaBianchengSixiang/img/saved.png
JavaBianchengSixiang/img/settings-s.png
JavaBianchengSixiang/img/settings.png
JavaBianchengSixiang/img/star.png
JavaBianchengSixiang/js/__init__.py
JavaBianchengSixiang/js/epub.js
JavaBianchengSixiang/js/epub.min.js
JavaBianchengSixiang/js/epub.min.map
JavaBianchengSixiang/js/hooks.min.js
JavaBianchengSixiang/js/hooks.min.map
JavaBianchengSixiang/js/reader.js
JavaBianchengSixiang/js/reader.js.map
JavaBianchengSixiang/js/reader.min.js
JavaBianchengSixiang/js/reader.min.map
JavaBianchengSixiang/js/hooks/__init__.py
JavaBianchengSixiang/js/hooks/extensions/__init__.py
JavaBianchengSixiang/js/hooks/extensions/highlight.js
JavaBianchengSixiang/js/libs/__init__.py
JavaBianchengSixiang/js/libs/jquery.min.js
JavaBianchengSixiang/js/libs/localforage.min.js
JavaBianchengSixiang/js/libs/screenfull.js
JavaBianchengSixiang/js/libs/screenfull.min.js
JavaBianchengSixiang/js/libs/zip.min.js
JavaBianchengSixiang/js/plugins/__init__.py
JavaBianchengSixiang/js/plugins/hypothesis.js
java_biancheng_sixiang-2024.3.2.0.dist-info/METADATA
java_biancheng_sixiang-2024.3.2.0.dist-info/WHEEL
java_biancheng_sixiang-2024.3.2.0.dist-info/entry_points.txt
java_biancheng_sixiang-2024.3.2.0.dist-info/top_level.txt
java_biancheng_sixiang-2024.3.2.0.dist-info/RECORD
